MANIFEST.in
README.md
VERSION.txt
setup.py
dataflows_serverless/__init__.py
dataflows_serverless/cli.py
dataflows_serverless/constants.py
dataflows_serverless/flow.py
dataflows_serverless/k8s.py
dataflows_serverless/primary_chain.py
dataflows_serverless/secondary_chain.py
dataflows_serverless/serverless_chain.py
dataflows_serverless.egg-info/PKG-INFO
dataflows_serverless.egg-info/SOURCES.txt
dataflows_serverless.egg-info/dependency_links.txt
dataflows_serverless.egg-info/entry_points.txt
dataflows_serverless.egg-info/requires.txt
dataflows_serverless.egg-info/top_level.txt
dataflows_serverless/bin/gke_cleanup.sh
dataflows_serverless/bin/gke_connect_or_create.sh
dataflows_serverless/bin/local_runner.sh
dataflows_serverless/templates/nfs-deployment.yaml
dataflows_serverless/templates/nfs-service.yaml
dataflows_serverless/templates/primary-job.yaml
dataflows_serverless/templates/secondary-job.yaml