Metadata-Version: 1.0
Name: dataflows-serverless
Version: 0.0.1
Summary: Use the DataFlows library using serverless concepts.
Home-page: https://github.com/OriHoch/dataflows-serverless
Author: Ori Hoch
Author-email: ori@uumpa.com
License: MIT
Platform: UNKNOWN
